{
    "compos": [
        {
            "width": 29,
            "position": {
                "column_min": 399,
                "row_min": 48,
                "column_max": 428,
                "row_max": 74
            },
            "class": "Compo",
            "id": 0,
            "height": 26
        },
        {
            "width": 27,
            "position": {
                "column_min": 29,
                "row_min": 77,
                "column_max": 56,
                "row_max": 83
            },
            "class": "Compo",
            "id": 1,
            "height": 6
        },
        {
            "width": 65,
            "position": {
                "column_min": 39,
                "row_min": 117,
                "column_max": 104,
                "row_max": 183
            },
            "class": "Compo",
            "id": 2,
            "height": 66
        },
        {
            "width": 12,
            "position": {
                "column_min": 51,
                "row_min": 201,
                "column_max": 63,
                "row_max": 219
            },
            "class": "Compo",
            "id": 3,
            "height": 18
        },
        {
            "width": 12,
            "position": {
                "column_min": 139,
                "row_min": 201,
                "column_max": 151,
                "row_max": 219
            },
            "class": "Compo",
            "id": 4,
            "height": 18
        },
        {
            "width": 12,
            "position": {
                "column_min": 226,
                "row_min": 201,
                "column_max": 238,
                "row_max": 219
            },
            "class": "Compo",
            "id": 5,
            "height": 18
        },
        {
            "width": 108,
            "children": [
                39
            ],
            "position": {
                "column_min": 324,
                "row_min": 203,
                "column_max": 432,
                "row_max": 241
            },
            "class": "Compo",
            "id": 6,
            "height": 38
        },
        {
            "width": 449,
            "children": [
                43,
                44
            ],
            "position": {
                "column_min": 0,
                "row_min": 266,
                "column_max": 449,
                "row_max": 320
            },
            "class": "Compo",
            "id": 7,
            "height": 54
        },
        {
            "width": 31,
            "position": {
                "column_min": 121,
                "row_min": 354,
                "column_max": 152,
                "row_max": 387
            },
            "class": "Compo",
            "id": 8,
            "height": 33
        },
        {
            "width": 42,
            "position": {
                "column_min": 200,
                "row_min": 355,
                "column_max": 242,
                "row_max": 394
            },
            "class": "Compo",
            "id": 9,
            "height": 39
        },
        {
            "width": 40,
            "position": {
                "column_min": 375,
                "row_min": 355,
                "column_max": 415,
                "row_max": 395
            },
            "class": "Compo",
            "id": 10,
            "height": 40
        },
        {
            "width": 25,
            "position": {
                "column_min": 38,
                "row_min": 356,
                "column_max": 63,
                "row_max": 385
            },
            "class": "Compo",
            "id": 11,
            "height": 29
        },
        {
            "width": 30,
            "position": {
                "column_min": 296,
                "row_min": 357,
                "column_max": 326,
                "row_max": 383
            },
            "class": "Compo",
            "id": 12,
            "height": 26
        },
        {
            "width": 28,
            "position": {
                "column_min": 37,
                "row_min": 479,
                "column_max": 65,
                "row_max": 506
            },
            "class": "Compo",
            "id": 13,
            "height": 27
        },
        {
            "width": 30,
            "position": {
                "column_min": 122,
                "row_min": 476,
                "column_max": 152,
                "row_max": 508
            },
            "class": "Compo",
            "id": 14,
            "height": 32
        },
        {
            "width": 37,
            "position": {
                "column_min": 207,
                "row_min": 477,
                "column_max": 244,
                "row_max": 509
            },
            "class": "Compo",
            "id": 15,
            "height": 32
        },
        {
            "width": 28,
            "position": {
                "column_min": 297,
                "row_min": 479,
                "column_max": 325,
                "row_max": 505
            },
            "class": "Compo",
            "id": 16,
            "height": 26
        },
        {
            "width": 28,
            "position": {
                "column_min": 384,
                "row_min": 477,
                "column_max": 412,
                "row_max": 508
            },
            "class": "Compo",
            "id": 17,
            "height": 31
        },
        {
            "width": 30,
            "position": {
                "column_min": 209,
                "row_min": 570,
                "column_max": 239,
                "row_max": 603
            },
            "class": "Compo",
            "id": 18,
            "height": 33
        },
        {
            "width": 29,
            "position": {
                "column_min": 383,
                "row_min": 570,
                "column_max": 412,
                "row_max": 603
            },
            "class": "Compo",
            "id": 19,
            "height": 33
        },
        {
            "width": 32,
            "position": {
                "column_min": 35,
                "row_min": 571,
                "column_max": 67,
                "row_max": 602
            },
            "class": "Compo",
            "id": 20,
            "height": 31
        },
        {
            "width": 28,
            "position": {
                "column_min": 123,
                "row_min": 572,
                "column_max": 151,
                "row_max": 602
            },
            "class": "Compo",
            "id": 21,
            "height": 30
        },
        {
            "width": 31,
            "position": {
                "column_min": 295,
                "row_min": 571,
                "column_max": 326,
                "row_max": 602
            },
            "class": "Compo",
            "id": 22,
            "height": 31
        },
        {
            "width": 15,
            "position": {
                "column_min": 217,
                "row_min": 654,
                "column_max": 232,
                "row_max": 661
            },
            "class": "Compo",
            "id": 23,
            "height": 7
        },
        {
            "width": 14,
            "position": {
                "column_min": 396,
                "row_min": 664,
                "column_max": 410,
                "row_max": 674
            },
            "class": "Compo",
            "id": 24,
            "height": 10
        },
        {
            "width": 15,
            "position": {
                "column_min": 360,
                "row_min": 668,
                "column_max": 375,
                "row_max": 674
            },
            "class": "Compo",
            "id": 25,
            "height": 6
        },
        {
            "width": 431,
            "children": [
                60,
                61,
                62,
                63
            ],
            "position": {
                "column_min": 9,
                "row_min": 676,
                "column_max": 440,
                "row_max": 788
            },
            "class": "Compo",
            "id": 26,
            "height": 112
        },
        {
            "width": 28,
            "position": {
                "column_min": 30,
                "row_min": 793,
                "column_max": 58,
                "row_max": 824
            },
            "class": "Compo",
            "id": 27,
            "height": 31
        },
        {
            "width": 32,
            "position": {
                "column_min": 118,
                "row_min": 794,
                "column_max": 150,
                "row_max": 824
            },
            "class": "Compo",
            "id": 28,
            "height": 30
        },
        {
            "width": 50,
            "position": {
                "column_min": 199,
                "row_min": 795,
                "column_max": 249,
                "row_max": 844
            },
            "class": "Compo",
            "id": 29,
            "height": 49
        },
        {
            "width": 32,
            "position": {
                "column_min": 298,
                "row_min": 793,
                "column_max": 330,
                "row_max": 825
            },
            "class": "Compo",
            "id": 30,
            "height": 32
        },
        {
            "width": 28,
            "position": {
                "column_min": 390,
                "row_min": 794,
                "column_max": 418,
                "row_max": 823
            },
            "class": "Compo",
            "id": 31,
            "height": 29
        },
        {
            "width": 120,
            "text_content": "1m",
            "position": {
                "column_min": 288,
                "row_min": 46,
                "column_max": 408,
                "row_max": 76
            },
            "class": "Text",
            "id": 32,
            "height": 30
        },
        {
            "width": 55,
            "text_content": "\u6211\u7684",
            "position": {
                "column_min": 15,
                "row_min": 47,
                "column_max": 70,
                "row_max": 78
            },
            "class": "Text",
            "id": 33,
            "height": 31
        },
        {
            "width": 44,
            "text_content": "\u521b\u4f5c",
            "position": {
                "column_min": 95,
                "row_min": 50,
                "column_max": 139,
                "row_max": 73
            },
            "class": "Text",
            "id": 34,
            "height": 23
        },
        {
            "width": 44,
            "text_content": "\u6d88\u606f",
            "position": {
                "column_min": 164,
                "row_min": 50,
                "column_max": 208,
                "row_max": 73
            },
            "class": "Text",
            "id": 35,
            "height": 23
        },
        {
            "width": 43,
            "text_content": "\u65b0\u4eba\u793c",
            "position": {
                "column_min": 212,
                "row_min": 111,
                "column_max": 255,
                "row_max": 127
            },
            "class": "Text",
            "id": 36,
            "height": 16
        },
        {
            "width": 92,
            "text_content": "\u7acb\u5373\u767b\u5f55",
            "position": {
                "column_min": 119,
                "row_min": 125,
                "column_max": 211,
                "row_max": 149
            },
            "class": "Text",
            "id": 37,
            "height": 24
        },
        {
            "width": 153,
            "text_content": "\u65b0\u7528\u6237\u767b\u5f55\u53ef\u9886vip\u6743\u76ca",
            "position": {
                "column_min": 120,
                "row_min": 160,
                "column_max": 273,
                "row_max": 175
            },
            "class": "Text",
            "id": 38,
            "height": 15
        },
        {
            "width": 65,
            "parent": 6,
            "text_content": "\u5f55\u97f3/\u76f4\u64ad",
            "position": {
                "column_min": 358,
                "row_min": 212,
                "column_max": 423,
                "row_max": 229
            },
            "class": "Text",
            "id": 39,
            "height": 17
        },
        {
            "width": 36,
            "text_content": "\u7c89\u4e1d",
            "position": {
                "column_min": 40,
                "row_min": 227,
                "column_max": 76,
                "row_max": 247
            },
            "class": "Text",
            "id": 40,
            "height": 20
        },
        {
            "width": 35,
            "text_content": "\u5173\u6ce8",
            "position": {
                "column_min": 128,
                "row_min": 227,
                "column_max": 163,
                "row_max": 248
            },
            "class": "Text",
            "id": 41,
            "height": 21
        },
        {
            "width": 36,
            "text_content": "\u4f5c\u54c1",
            "position": {
                "column_min": 215,
                "row_min": 227,
                "column_max": 251,
                "row_max": 248
            },
            "class": "Text",
            "id": 42,
            "height": 21
        },
        {
            "width": 94,
            "parent": 7,
            "text_content": "VIP\u9996\u6708\u4ec56\u5143",
            "position": {
                "column_min": 74,
                "row_min": 285,
                "column_max": 168,
                "row_max": 302
            },
            "class": "Text",
            "id": 43,
            "height": 17
        },
        {
            "width": 85,
            "parent": 7,
            "text_content": "\u7279\u9080\u9650\u65f6\u4e13\u4eab>",
            "position": {
                "column_min": 320,
                "row_min": 287,
                "column_max": 405,
                "row_max": 300
            },
            "class": "Text",
            "id": 44,
            "height": 13
        },
        {
            "width": 38,
            "text_content": "\u8ba2\u9605",
            "position": {
                "column_min": 31,
                "row_min": 395,
                "column_max": 69,
                "row_max": 417
            },
            "class": "Text",
            "id": 45,
            "height": 22
        },
        {
            "width": 37,
            "text_content": "\u4e0b\u8f7d",
            "position": {
                "column_min": 206,
                "row_min": 395,
                "column_max": 243,
                "row_max": 417
            },
            "class": "Text",
            "id": 46,
            "height": 22
        },
        {
            "width": 37,
            "text_content": "\u559c\u6b22",
            "position": {
                "column_min": 293,
                "row_min": 397,
                "column_max": 330,
                "row_max": 417
            },
            "class": "Text",
            "id": 47,
            "height": 20
        },
        {
            "width": 67,
            "text_content": "\u64ad\u653e\u5386\u53f2",
            "position": {
                "column_min": 104,
                "row_min": 397,
                "column_max": 171,
                "row_max": 416
            },
            "class": "Text",
            "id": 48,
            "height": 19
        },
        {
            "width": 67,
            "text_content": "\u5494\u566a\u7b14\u8bb0",
            "position": {
                "column_min": 365,
                "row_min": 397,
                "column_max": 432,
                "row_max": 416
            },
            "class": "Text",
            "id": 49,
            "height": 19
        },
        {
            "width": 39,
            "text_content": "\u94b1\u5305",
            "position": {
                "column_min": 31,
                "row_min": 518,
                "column_max": 70,
                "row_max": 540
            },
            "class": "Text",
            "id": 50,
            "height": 22
        },
        {
            "width": 37,
            "text_content": "\u8ba2\u5355",
            "position": {
                "column_min": 118,
                "row_min": 519,
                "column_max": 155,
                "row_max": 538
            },
            "class": "Text",
            "id": 51,
            "height": 19
        },
        {
            "width": 54,
            "text_content": "\u8d2d\u7269\u8f66",
            "position": {
                "column_min": 197,
                "row_min": 518,
                "column_max": 251,
                "row_max": 539
            },
            "class": "Text",
            "id": 52,
            "height": 21
        },
        {
            "width": 36,
            "text_content": "\u5df2\u8d2d",
            "position": {
                "column_min": 294,
                "row_min": 520,
                "column_max": 330,
                "row_max": 539
            },
            "class": "Text",
            "id": 53,
            "height": 19
        },
        {
            "width": 68,
            "text_content": "\u514d\u6d41\u670d\u52a1",
            "position": {
                "column_min": 363,
                "row_min": 519,
                "column_max": 431,
                "row_max": 539
            },
            "class": "Text",
            "id": 54,
            "height": 20
        },
        {
            "width": 37,
            "text_content": "\u5b9a\u65f6",
            "position": {
                "column_min": 206,
                "row_min": 612,
                "column_max": 243,
                "row_max": 633
            },
            "class": "Text",
            "id": 55,
            "height": 21
        },
        {
            "width": 68,
            "text_content": "\u8054\u7cfb\u5ba2\u670d",
            "position": {
                "column_min": 17,
                "row_min": 614,
                "column_max": 85,
                "row_max": 632
            },
            "class": "Text",
            "id": 56,
            "height": 18
        },
        {
            "width": 67,
            "text_content": "\u5b98\u65b9\u5546\u57ce",
            "position": {
                "column_min": 104,
                "row_min": 614,
                "column_max": 171,
                "row_max": 632
            },
            "class": "Text",
            "id": 57,
            "height": 18
        },
        {
            "width": 37,
            "text_content": "\u501f\u94b1",
            "position": {
                "column_min": 293,
                "row_min": 612,
                "column_max": 330,
                "row_max": 633
            },
            "class": "Text",
            "id": 58,
            "height": 21
        },
        {
            "width": 66,
            "text_content": "\u6d4f\u89c8\u5386\u53f2",
            "position": {
                "column_min": 365,
                "row_min": 614,
                "column_max": 431,
                "row_max": 632
            },
            "class": "Text",
            "id": 59,
            "height": 18
        },
        {
            "width": 75,
            "parent": 26,
            "text_content": "\u6210\u957f\u798f\u5229",
            "position": {
                "column_min": 20,
                "row_min": 708,
                "column_max": 95,
                "row_max": 728
            },
            "class": "Text",
            "id": 60,
            "height": 20
        },
        {
            "width": 181,
            "parent": 26,
            "text_content": "\u79ef\u5206\u5f53\u94b1\u82b1\uff0c\u597d\u793c\u5151\u4e0d\u505c",
            "position": {
                "column_min": 107,
                "row_min": 710,
                "column_max": 288,
                "row_max": 727
            },
            "class": "Text",
            "id": 61,
            "height": 17
        },
        {
            "width": 89,
            "parent": 26,
            "text_content": "\u79ef\u5206\u5151\u597d\u793c",
            "position": {
                "column_min": 94,
                "row_min": 757,
                "column_max": 183,
                "row_max": 775
            },
            "class": "Text",
            "id": 62,
            "height": 18
        },
        {
            "width": 57,
            "parent": 26,
            "text_content": "\u7d2f\u8ba1\u6536\u542c",
            "position": {
                "column_min": 310,
                "row_min": 759,
                "column_max": 367,
                "row_max": 775
            },
            "class": "Text",
            "id": 63,
            "height": 16
        },
        {
            "width": 30,
            "text_content": "\u6211\u542c",
            "position": {
                "column_min": 119,
                "row_min": 827,
                "column_max": 149,
                "row_max": 846
            },
            "class": "Text",
            "id": 64,
            "height": 19
        },
        {
            "width": 28,
            "text_content": "\u9996\u9875",
            "position": {
                "column_min": 31,
                "row_min": 829,
                "column_max": 59,
                "row_max": 844
            },
            "class": "Text",
            "id": 65,
            "height": 15
        },
        {
            "width": 29,
            "text_content": "\u53d1\u73b0",
            "position": {
                "column_min": 300,
                "row_min": 828,
                "column_max": 329,
                "row_max": 845
            },
            "class": "Text",
            "id": 66,
            "height": 17
        },
        {
            "width": 41,
            "text_content": "\u672a\u767b\u5f55",
            "position": {
                "column_min": 384,
                "row_min": 829,
                "column_max": 425,
                "row_max": 845
            },
            "class": "Text",
            "id": 67,
            "height": 16
        }
    ],
    "img_shape": [
        900,
        450,
        3
    ]
}